{ "otherData": {}, "traceEvents": [{"cat":"function","dur":1498,"name":"void __cdecl NGN::Renderer2D::Shutdown(void)","ph":"X","pid":0,"tid":1593619730, "ts":46300851323},{"cat":"function","dur":1567,"name":"void __cdecl NGN::Renderer::Shutdown(void)","ph":"X","pid":0,"tid":1593619730, "ts":46300851323},{"cat":"function","dur":1589,"name":"__cdecl NGN::Application::~Application(void)","ph":"X","pid":0,"tid":1593619730, "ts":46300851323},{"cat":"function","dur":42952,"name":"void __cdecl NGN::WinWindow::Shutdown(void)","ph":"X","pid":0,"tid":1593619730, "ts":46300852997},{"cat":"function","dur":43041,"name":"__cdecl NGN::WinWindow::~WinWindow(void)","ph":"X","pid":0,"tid":1593619730, "ts":46300852997}]}